{
    "file_name": "2024.0397 - Aqua-Tots - Full Set - 10.17.24.pdf_page59.png",
    "annotations": [
        {
            "text": "SHOPPING CENTER",
            "bbox": [
                63.0,
                8.0,
                201.0,
                25.0
            ],
            "confidence": 0.9609375
        },
        {
            "text": "PYRIGHT @ 2024 INTERPLAN LLC RESERVES COPYRIGHT & OTHER RIGHTS RESTR",
            "bbox": [
                220.0,
                13.0,
                230.0,
                243.0
            ],
            "confidence": 0.96533203125
        },
        {
            "text": "2133 UPTON DRIVE SUITE 100",
            "bbox": [
                55.0,
                40.0,
                208.0,
                51.0
            ],
            "confidence": 0.994140625
        },
        {
            "text": "VIRGINIA BEACH, VIRGINIA",
            "bbox": [
                58.0,
                57.0,
                205.0,
                69.0
            ],
            "confidence": 0.994140625
        },
        {
            "text": "23454",
            "bbox": [
                115.0,
                76.0,
                148.0,
                86.0
            ],
            "confidence": 0.9951171875
        },
        {
            "text": "PROJECT NO: 2024.0397",
            "bbox": [
                56.0,
                109.0,
                164.0,
                117.0
            ],
            "confidence": 0.9833984375
        },
        {
            "text": "DATE:",
            "bbox": [
                56.0,
                124.0,
                82.0,
                132.0
            ],
            "confidence": 0.96142578125
        },
        {
            "text": "POOL SECTIONS",
            "bbox": [
                92.0,
                159.0,
                171.0,
                169.0
            ],
            "confidence": 0.9794921875
        },
        {
            "text": "CHECKED: IP",
            "bbox": [
                57.0,
                244.0,
                111.0,
                252.0
            ],
            "confidence": 0.98193359375
        },
        {
            "text": "DRAWN: NA",
            "bbox": [
                128.0,
                244.0,
                179.0,
                252.0
            ],
            "confidence": 0.9775390625
        }
    ]
}